httpy/__init__.py
httpy/__main__.py
httpy/arguments.py
httpy/core.py
httpy/request.py
httpy/status.py
httpy/command/__init__.py
httpy/command/builder.py
httpy/command/handler.py
httpy/command/operation.py
httpy/command/regexs.py
httpy/output/__init__.py
httpy/output/colors.py
httpy/output/error.py
httpy/output/http.py
httpy/output/lexers.py
httpy/output/writer.py
httpy_cli-1.1.0.dist-info/LICENSE
httpy_cli-1.1.0.dist-info/METADATA
httpy_cli-1.1.0.dist-info/WHEEL
httpy_cli-1.1.0.dist-info/entry_points.txt
httpy_cli-1.1.0.dist-info/top_level.txt
httpy_cli-1.1.0.dist-info/RECORD
