Metadata-Version: 2.1
Name: httpy-cli
Version: 1.1.0
Summary: Modern, user-friendly, programmable command-line HTTP client for the API.
Download-URL: https://github.com/SinanKanidagli/httpy/archive/refs/tags/httpy-0.0.1.tar.gz
Author: Sinan Kanidağlı
Author-email: sinan_kanidagli@hotmail.com
License: MIT
Project-URL: GitHub, https://github.com/SinanKanidagli/httpy
Project-URL: Twitter, https://twitter.com/KanidagliV
Project-URL: Documentation, https://github.com/SinanKanidagli/httpy/docs
Classifier: Development Status :: 5 - Production/Stable
Classifier: Programming Language :: Python
Classifier: Programming Language :: Python :: 3 :: Only
Classifier: Environment :: Console
Classifier: Intended Audience :: Developers
Classifier: Intended Audience :: System Administrators
Classifier: License :: OSI Approved :: MIT License
Classifier: Topic :: Internet :: WWW/HTTP
Classifier: Topic :: Software Development
Classifier: Topic :: System :: Networking
Classifier: Topic :: Terminals
Classifier: Topic :: Text Processing
Classifier: Topic :: Utilities
Requires-Python: >=3.7
License-File: LICENSE
Requires-Dist: requests (>=2.27.0)
Requires-Dist: Pygments (>=2.5.2)
Requires-Dist: setuptools
Requires-Dist: colorama (>=0.4.4) ; sys_platform == "win32"
Provides-Extra: dev
Requires-Dist: pytest ; extra == 'dev'
Requires-Dist: flake8 ; extra == 'dev'
Requires-Dist: pyyaml ; extra == 'dev'
Requires-Dist: twine ; extra == 'dev'
Requires-Dist: wheel ; extra == 'dev'
Provides-Extra: test
Requires-Dist: pytest ; extra == 'test'
